modeldag/__init__.py
modeldag/modeldag.py
modeldag/tools.py
modeldag-0.11.1.dist-info/licenses/LICENSE
modeldag-0.11.1.dist-info/METADATA
modeldag-0.11.1.dist-info/WHEEL
modeldag-0.11.1.dist-info/top_level.txt
modeldag-0.11.1.dist-info/RECORD
